__init__.py
__main__.py
cli.py
server.py
tools.py
iflow_mcp_atharvagupta2003_mcp_stripe-0.1.5.dist-info/licenses/LICENSE
iflow_mcp_atharvagupta2003_mcp_stripe-0.1.5.dist-info/METADATA
iflow_mcp_atharvagupta2003_mcp_stripe-0.1.5.dist-info/WHEEL
iflow_mcp_atharvagupta2003_mcp_stripe-0.1.5.dist-info/entry_points.txt
iflow_mcp_atharvagupta2003_mcp_stripe-0.1.5.dist-info/top_level.txt
iflow_mcp_atharvagupta2003_mcp_stripe-0.1.5.dist-info/RECORD
