Metadata-Version: 2.4
Name: iflow-mcp_atharvagupta2003_mcp-stripe
Version: 0.1.5
Summary: MCP server for Stripe payments, customers, and refunds
Requires-Python: >=3.11
License-File: LICENSE
Requires-Dist: httpx>=0.28.1
Requires-Dist: mcp[cli]>=1.2.1
Requires-Dist: stripe>=11.0.0
Requires-Dist: python-dotenv>=1.0.0
Dynamic: license-file
